Metadata-Version: 1.0
Name: bow-distributions
Version: 1.9
Summary: Gaussian distributions & Binomial distributions
Home-page: https://github.com/AnalystBow/myPythonPackages
Author: Waliyat Olayiwola
Author-email: analystbow@gmail.com
License: UNKNOWN
Platform: UNKNOWN
